{
  "sections": {
    "c_tailwind_CPDFXf": {
      "type": "c-tailwind",
      "settings": {}
    },
    "banner": {
      "type": "main-collection-banner",
      "disabled": true,
      "custom_css": [
        ".collection-hero__title {font-size: 2em;}",
        "@media (min-width: 750px) {.collection-hero__title {font-size: 3em; }}"
      ],
      "settings": {
        "show_collection_description": true,
        "show_collection_image": false,
        "color_scheme": "background-1"
      }
    },
    "product-grid": {
      "type": "main-collection-product-grid",
      "disabled": true,
      "settings": {
        "products_per_page": 16,
        "columns_desktop": 4,
        "image_ratio": "adapt",
        "show_secondary_image": false,
        "show_vendor": false,
        "show_rating": true,
        "enable_quick_add": false,
        "enable_filtering": true,
        "filter_type": "vertical",
        "enable_sorting": true,
        "columns_mobile": "2",
        "padding_top": 20,
        "padding_bottom": 40
      }
    },
    "17716680683b37038a": {
      "type": "_blocks",
      "blocks": {
        "ai_gen_block_0f1ce08_A4kQYQ": {
          "type": "ai_gen_block_0f1ce08",
          "settings": {
            "image": "shopify:\/\/shop_images\/5fbe2a40f13296cbd5b526113cac73d54693fc90.png",
            "desktop_width_percent": 100,
            "max_width": 1400,
            "image_height": "auto",
            "custom_height": 400,
            "mobile_image_height": "auto",
            "mobile_custom_height": 800,
            "object_fit": "contain",
            "border_radius": 22,
            "margin_top": 20,
            "margin_bottom": 0,
            "margin_left": 0,
            "margin_right": 0,
            "background_color": "#eeeeee"
          },
          "blocks": {}
        }
      },
      "block_order": [
        "ai_gen_block_0f1ce08_A4kQYQ"
      ],
      "settings": {}
    },
    "1771767251e756f691": {
      "type": "_blocks",
      "blocks": {
        "ai_gen_block_6707cba_fYMk8r": {
          "type": "ai_gen_block_6707cba",
          "settings": {
            "container_width": 1500,
            "section_padding": 40,
            "grid_gap": 30,
            "sidebar_width": 280,
            "sidebar_radius": 14,
            "sidebar_bg": "#ffffff",
            "sidebar_border": "#e5e5e5",
            "divider_color": "#1878b9",
            "show_price_filter": true,
            "max_price": 9000,
            "products_per_row": 3,
            "products_limit": 12,
            "product_gap": 20,
            "card_radius": 14,
            "btn_radius": 14,
            "card_bg": "#ffffff",
            "card_border": "#e8e8e8",
            "page_bg": "#eeeeee",
            "text_color": "#000000",
            "accent_color": "#0070f3",
            "btn_bg": "#111111",
            "btn_color": "#ffffff",
            "preorder_btn_bg": "#5a3e8c",
            "preorder_btn_color": "#ffffff",
            "badge_bg": "#e53e3e",
            "badge_color": "#ffffff",
            "preorder_badge_bg": "#5a3e8c",
            "preorder_badge_color": "#ffffff",
            "discount_tag_bg": "#e5e5e5",
            "discount_tag_color": "#856404"
          },
          "blocks": {}
        }
      },
      "block_order": [
        "ai_gen_block_6707cba_fYMk8r"
      ],
      "settings": {}
    }
  },
  "order": [
    "c_tailwind_CPDFXf",
    "banner",
    "product-grid",
    "17716680683b37038a",
    "1771767251e756f691"
  ]
}
